README.md
setup.py
API use cases/Compute-maximum-reachable-altitude.py
API use cases/Constellations_revisit_rate_evolution.py
API use cases/Full-mission-simulation.py
API use cases/Pause-capability-in-simulation-missions.py
API use cases/Simple_RAAN_mission.py
API use cases/__init__.py
API use cases/use_cases_tools.py
spacestudio/__init__.py
spacestudio/api_requests.py
spacestudio/constellation.py
spacestudio/deployment.py
spacestudio/formation_flying.py
spacestudio/gridfs.py
spacestudio/inspection.py
spacestudio/parametric_study.py
spacestudio/simulation.py
spacestudio/urls.py
spacestudio_constellation.egg-info/PKG-INFO
spacestudio_constellation.egg-info/SOURCES.txt
spacestudio_constellation.egg-info/dependency_links.txt
spacestudio_constellation.egg-info/requires.txt
spacestudio_constellation.egg-info/top_level.txt