Metadata-Version: 2.1
Name: spacestudio-constellation
Version: 3.4.0
Summary: spacestudio™ constellation scripting API
Author: Exotrail
Author-email: support.spacestudio@exotrail.com
Keywords: spacestudio constellation scripting propulsion
Classifier: Development Status :: 5 - Production/Stable
Classifier: Intended Audience :: End Users/Desktop
Classifier: Programming Language :: Python :: 3
Requires-Dist: requests
Requires-Dist: pyjwt
Requires-Dist: openpyxl
Requires-Dist: python-dotenv
Requires-Dist: numpy
Requires-Dist: matplotlib
